{
  "$schema": "https://dl.viam.dev/module.schema.json",
  "module_id": "vinnyhuang:person-detector",
  "visibility": "private",
  "url": "",
  "description": "Modular sensor component: people-sensor",
  "models": [
    {
      "api": "rdk:component:sensor",
      "model": "vinnyhuang:person-detector:people-sensor",
      "short_description": "Sensor that indicates whether person is detected by camera",
      "markdown_link": "README.md#model-vinnyhuangperson-detectorpeople-sensor"
    }
  ],
  "applications": null,
  "markdown_link": "README.md",
  "entrypoint": "./run.sh",
  "first_run": "",
  "build": {
    "build": "./build.sh",
    "setup": "./setup.sh",
    "path": "dist/archive.tar.gz",
    "arch": [
      "linux/amd64",
      "linux/arm64"
    ]
  }
}